setup.py
callbackToReturnVal/__init__.py
callbackToReturnVal.egg-info/PKG-INFO
callbackToReturnVal.egg-info/SOURCES.txt
callbackToReturnVal.egg-info/dependency_links.txt
callbackToReturnVal.egg-info/top_level.txt