Metadata-Version: 1.0
Name: callbackToReturnVal
Version: 0.1.2
Summary: Wrapper function that returns the value that is sent to a callback value as the value that the wrapper gives
Home-page: http://github.com/theblazehen/python-callbackToReturnVal
Author: Jeandre Le Roux
Author-email: theblazehen@theblazehen.com
License: MIT
Platform: UNKNOWN
